README.md
setup.py
amit/__init__.py
amit/__main__.py
amit/config.py
amit/constants.py
amit/database.py
amit/interactive.py
amit/interactive_add.py
amit/interactive_enum.py
amit/interactive_report.py
amit/interactive_scan.py
amit/interactive_show.py
amit/jobs.py
amit.egg-info/PKG-INFO
amit.egg-info/SOURCES.txt
amit.egg-info/dependency_links.txt
amit.egg-info/not-zip-safe
amit.egg-info/top_level.txt
bin/amit