Metadata-Version: 2.1
Name: amit
Version: 1.0
Summary: A pentest enumeration framework
Home-page: http://github.com/polyedre/amit
Author: Lucas Henry
Author-email: lucas.henry@enseirb-matmeca.fr
License: GPL
Platform: UNKNOWN
Classifier: Programming Language :: Python :: 3
Classifier: License :: OSI Approved :: GNU Affero General Public License v3 or later (AGPLv3+)
Classifier: Operating System :: OS Independent
